{
  "sections": {
    "suggestions": [
      {
        "data": {
          "groups": [
            {
              "display_name": "Drama",
              "group_id": "18",
              "path": null
            },
            {
              "display_name": "Romance",
              "group_id": "10749",
              "path": null
            },
            {
              "display_name": "Thriller",
              "group_id": "53",
              "path": null
            },
            {
              "display_name": "Action",
              "group_id": "28",
              "path": null
            },
            {
              "display_name": "Documentary",
              "group_id": "99",
              "path": null
            },
            {
              "display_name": "History",
              "group_id": "36",
              "path": null
            },
            {
              "display_name": "Adventure",
              "group_id": "12",
              "path": null
            }
          ],
          "id": "titanic"
        },
        "matched_terms": [
          "titanic"
        ],
        "value": "titanic"
      }
    ]
  }
}

